sm_serverless_benchmarking/__init__.py
sm_serverless_benchmarking/__main__.py
sm_serverless_benchmarking/analysis.py
sm_serverless_benchmarking/benchmark.py
sm_serverless_benchmarking/cost_constants.py
sm_serverless_benchmarking/endpoint.py
sm_serverless_benchmarking/report.py
sm_serverless_benchmarking/requirements.txt
sm_serverless_benchmarking/sagemaker_runner.py
sm_serverless_benchmarking/utils.py
sm_serverless_benchmarking/report_templates/__init__.py
sm_serverless_benchmarking/report_templates/report_template.html
sm_serverless_benchmarking-0.2.3.dist-info/LICENSE
sm_serverless_benchmarking-0.2.3.dist-info/METADATA
sm_serverless_benchmarking-0.2.3.dist-info/WHEEL
sm_serverless_benchmarking-0.2.3.dist-info/top_level.txt
sm_serverless_benchmarking-0.2.3.dist-info/RECORD
