Metadata-Version: 2.1
Name: sm-serverless-benchmarking
Version: 0.2.3
Summary: Benchmark sagemaker serverless endpoints for cost and performance
Author: Amazon Web Services
License: Copyright Amazon.com, Inc. or its affiliates. All Rights Reserved.
Keywords: sagemaker,inference,hosting
Classifier: License :: OSI Approved :: MIT License
Classifier: Programming Language :: Python
Classifier: Programming Language :: Python :: 3
Requires-Python: >=3.7
License-File: LICENSE
Requires-Dist: boto3 <2.0,>=1.20.21
Requires-Dist: pandas
Requires-Dist: seaborn
Requires-Dist: Jinja2
Requires-Dist: numpy
Requires-Dist: matplotlib
Requires-Dist: tomli ; python_version < "3.11"
Provides-Extra: dev
Requires-Dist: black ; extra == 'dev'
Requires-Dist: bumpver ; extra == 'dev'
Requires-Dist: isort ; extra == 'dev'
Requires-Dist: pip-tools ; extra == 'dev'
Provides-Extra: sagemaker
Requires-Dist: sagemaker <3.0,>2.0 ; extra == 'sagemaker'
